debug/__init__.py
jc_debug-1.0.4.dist-info/licenses/LICENSE
jc_debug-1.0.4.dist-info/METADATA
jc_debug-1.0.4.dist-info/WHEEL
jc_debug-1.0.4.dist-info/top_level.txt
jc_debug-1.0.4.dist-info/RECORD
