Metadata-Version: 2.4
Name: jc-debug
Version: 1.0.4
Summary: Makes debugging to the console both simpler and much more powerful.
Author-email: Jeff Clough <jeff@cloughcottage.com>
License: MIT License
Project-URL: Homepage, https://github.com/jc-handy/debug
Keywords: utility,toolkit,convenience
Classifier: Development Status :: 5 - Production/Stable
Classifier: Intended Audience :: Developers
Classifier: License :: OSI Approved :: MIT License
Classifier: Programming Language :: Python :: 3
Classifier: Programming Language :: Python :: 3.11
Classifier: Operating System :: OS Independent
Requires-Python: >=3.11
License-File: LICENSE
Dynamic: license-file
